LICENSE
README.md
setup.cfg
setup.py
basepage/__init__.py
basepage/base_page.py
basepage/decorators.py
basepage/extended_expected_conditions.py
basepage/wait.py
basepage.egg-info/PKG-INFO
basepage.egg-info/SOURCES.txt
basepage.egg-info/dependency_links.txt
basepage.egg-info/top_level.txt