Metadata-Version: 2.1
Name: basepage
Version: 1.7.5
Summary: A wrapper for WebDriver that provides some extended and additional functionality
Home-page: https://github.com/Projectplace/basepage
Download-URL: https://github.com/Projectplace/basepage/tarball/1.7.5
Author: Bijwen Aziz
Author-email: baziz@planview.com
License: UNKNOWN
Keywords: testing,webdriver,selenium
Platform: UNKNOWN
Classifier: Development Status :: 5 - Production/Stable
Classifier: Framework :: Pytest
Classifier: Intended Audience :: Developers
Classifier: License :: OSI Approved :: Apache Software License
Classifier: Operating System :: POSIX
Classifier: Operating System :: Microsoft :: Windows
Classifier: Operating System :: MacOS :: MacOS X
Classifier: Topic :: Software Development :: Quality Assurance
Classifier: Topic :: Software Development :: Testing
Classifier: Topic :: Utilities
Classifier: Programming Language :: Python
Classifier: Programming Language :: Python :: 2.7
Classifier: Programming Language :: Python :: 3.5
Classifier: Programming Language :: Python :: 3.6
License-File: LICENSE
